[
  {
    "img": "https://images-na.ssl-images-amazon.com/images/I/41Onrb4HqxL._SL160_SL150_.jpg",
    "link": "https://www.amazon.com/Panda-Portable-Apartment-stainless-Window8-8lbs/dp/B0092JSGXI/ref=zg_bs_appliances_80",
    "price": "$249.99",
    "rank": "80",
    "review": "4.3(186)",
    "title": "Panda-Portable-Apartment-stainless-Window8-8lbs"
  },
  {
    "img": "https://images-na.ssl-images-amazon.com/images/I/419PZij%2B7SL._SL160_SL150_.jpg",
    "link": "https://www.amazon.com/Danby-Designer-0-9-Microwave-Oven/dp/B003XSST4A/ref=zg_bs_appliances_79",
    "price": "$109.00 $61.19",
    "rank": "79",
    "review": "3.9(1907)",
    "title": "Danby-Designer-0-9-Microwave-Oven"
  },
  {
    "img": "https://images-na.ssl-images-amazon.com/images/I/315Zf7Z7scL._SL160_SL150_.jpg",
    "link": "https://www.amazon.com/Cooluli-Electric-Cooler-Warmer-Liter/dp/B01G7IL476/ref=zg_bs_appliances_78",
    "price": "$53.99 $42.99",
    "rank": "78",
    "review": "4.5(55)",
    "title": "Cooluli-Electric-Cooler-Warmer-Liter"
  },
  {
    "img": "https://images-na.ssl-images-amazon.com/images/I/418rA%2BNHm%2BL._SL160_SL150_.jpg",
    "link": "https://www.amazon.com/Linkings-Beauty-Waterproof-Liquid-Lipstick/dp/B01LNMU24W/ref=zg_bs_appliances_77",
    "price": "$5.25",
    "rank": "77",
    "review": "4.4(29)",
    "title": "Linkings-Beauty-Waterproof-Liquid-Lipstick"
  },
  {
    "img": "https://images-na.ssl-images-amazon.com/images/I/41kNcc917NL._SL160_SL150_.jpg",
    "link": "https://www.amazon.com/Indoor-Lint-Trap-Filter-LTF0001/dp/B008RNPOIU/ref=zg_bs_appliances_76",
    "price": "$35.95",
    "rank": "76",
    "review": "4.4(326)",
    "title": "Indoor-Lint-Trap-Filter-LTF0001"
  },
  {
    "img": "https://images-na.ssl-images-amazon.com/images/I/41fyiTiPg4L._SL160_SL150_.jpg",
    "link": "https://www.amazon.com/Avalon-Bay-AB-ICE26S-Portable-Maker/dp/B00IY7BNUW/ref=zg_bs_appliances_75",
    "price": "$189.99 $145.00",
    "rank": "75",
    "review": "3.9(1283)",
    "title": "Avalon-Bay-AB-ICE26S-Portable-Maker"
  },
  {
    "img": "https://images-na.ssl-images-amazon.com/images/I/31d8UsCoj4L._SL160_SL150_.jpg",
    "link": "https://www.amazon.com/Laundry-Alternative-Portable-Countertop-Dryer/dp/B002HT0958/ref=zg_bs_appliances_74",
    "price": "$100.00 $69.99",
    "rank": "74",
    "review": "4.1(354)",
    "title": "Laundry-Alternative-Portable-Countertop-Dryer"
  },
  {
    "img": "https://images-na.ssl-images-amazon.com/images/I/51%2B9PH3BUTL._SL160_SL150_.jpg",
    "link": "https://www.amazon.com/Pure-Filters-Filter-Compatible-UKF8001/dp/B00UIZLE48/ref=zg_bs_appliances_73",
    "price": "",
    "rank": "73",
    "review": "4.3(907)",
    "title": "Pure-Filters-Filter-Compatible-UKF8001"
  },
  {
    "img": "https://images-na.ssl-images-amazon.com/images/I/21ZWS3uLPVL._SL160_SL150_.jpg",
    "link": "https://www.amazon.com/GE-Number-WB48X10056-Broiler-Large/dp/B004Q3XD1U/ref=zg_bs_appliances_72",
    "price": "$21.00",
    "rank": "72",
    "review": "4.5(284)",
    "title": "GE-Number-WB48X10056-Broiler-Large"
  },
  {
    "img": "https://images-na.ssl-images-amazon.com/images/I/41SpECQWrNL._SL160_SL150_.jpg",
    "link": "https://www.amazon.com/Compactor-Bags-Pre-Cuffed-Pack/dp/B00W27J16S/ref=zg_bs_appliances_71",
    "price": "$79.95",
    "rank": "71",
    "review": "4.9(64)",
    "title": "Compactor-Bags-Pre-Cuffed-Pack"
  },
  {
    "img": "https://images-na.ssl-images-amazon.com/images/I/41FF4hHsPYL._SL160_SL150_.jpg",
    "link": "https://www.amazon.com/Frigidaire-ULTRAWF-Compatible-Water-Filter/dp/B012YPVRIM/ref=zg_bs_appliances_70",
    "price": "",
    "rank": "70",
    "review": "4.1(1044)",
    "title": "Frigidaire-ULTRAWF-Compatible-Water-Filter"
  },
  {
    "img": "https://images-na.ssl-images-amazon.com/images/I/410HYFhfjML._SL160_SL150_.jpg",
    "link": "https://www.amazon.com/Liners-Included-Electric-Convection-Toaster/dp/B01GRKQA0K/ref=zg_bs_appliances_69",
    "price": "$13.95",
    "rank": "69",
    "review": "4.7(314)",
    "title": "Liners-Included-Electric-Convection-Toaster"
  },
  {
    "img": "https://images-na.ssl-images-amazon.com/images/I/41AxgNZnCWL._SL160_SL150_.jpg",
    "link": "https://www.amazon.com/Haier-HC27SF22RB-Cubic-Refrigerator-Freezer/dp/B00N142WLC/ref=zg_bs_appliances_68",
    "price": "$219.00 $123.20",
    "rank": "68",
    "review": "3.9(218)",
    "title": "Haier-HC27SF22RB-Cubic-Refrigerator-Freezer"
  },
  {
    "img": "https://images-na.ssl-images-amazon.com/images/I/315KZwsEHFL._SL160_SL150_.jpg",
    "link": "https://www.amazon.com/Samsung-Counter-Microwave-Mirror-Finish/dp/B00NQFSSWS/ref=zg_bs_appliances_67",
    "price": "$179.99",
    "rank": "67",
    "review": "3.9(348)",
    "title": "Samsung-Counter-Microwave-Mirror-Finish"
  },
  {
    "img": "https://images-na.ssl-images-amazon.com/images/I/414tCELWvNL._SL160_SL150_.jpg",
    "link": "https://www.amazon.com/Glacial-Pure-Replacement-Whirlpool-W10295370A/dp/B01HIZ4DZM/ref=zg_bs_appliances_66",
    "price": "$26.99 $14.95",
    "rank": "66",
    "review": "4.1(90)",
    "title": "Glacial-Pure-Replacement-Whirlpool-W10295370A"
  },
  {
    "img": "https://images-na.ssl-images-amazon.com/images/I/41TpZ%2BTMu9L._SL160_SL150_.jpg",
    "link": "https://www.amazon.com/WHS-87LSS1-Compact-Reversible-Refrigerator-Stainless/dp/B00MMRFQR6/ref=zg_bs_appliances_65",
    "price": "$102.93 $102.36",
    "rank": "65",
    "review": "4.1(725)",
    "title": "WHS-87LSS1-Compact-Reversible-Refrigerator-Stainless"
  },
  {
    "img": "https://images-na.ssl-images-amazon.com/images/I/41OrKWvZBDL._SL160_SL150_.jpg",
    "link": "https://www.amazon.com/Ice-Packs-Pcs-Reusable-Colorful/dp/B00GWDYD48/ref=zg_bs_appliances_64",
    "price": "$18.99 $14.95",
    "rank": "64",
    "review": "4.4(273)",
    "title": "Ice-Packs-Pcs-Reusable-Colorful"
  }
]
